{
  "generatedAt": "2026-06-20T19:58:35Z",
  "modelId": "wnba-player-prop-model-v1",
  "modelVersion": "2026-05-16-roster-slate-gate-v10",
  "cardGeneratedAt": "2026-06-20T19:58:35Z",
  "slateDate": "2026-06-20",
  "claimBoundary": "WNBA V1 uses historical boxscore logs plus supplied prop lines. It is a ranking and calibration model, not a guarantee. Live betting claims require current lines, player availability, and settled forward audit.",
  "summary": {
    "trackedPicks": 4,
    "settledPicks": 0,
    "pendingPicks": 4,
    "noActionPicks": 0,
    "wins": 0,
    "losses": 0,
    "pushes": 0,
    "accuracyPct": null
  },
  "rows": [
    {
      "slate_date": "2026-06-20",
      "selected_rank": 1,
      "player": "Azura Stevens",
      "team": "CHI",
      "team_name": "Chicago Sky",
      "opponent": "DAL",
      "opponent_name": "Dallas Wings",
      "market": "THREES",
      "side": "UNDER",
      "line": 1.5,
      "actual": null,
      "settlement": "PENDING",
      "model_probability": 0.77622,
      "final_score": 0.75724,
      "source_book": "bet365",
      "source_url": "https://www.scoresandodds.com/wnba/props/3-pointers"
    },
    {
      "slate_date": "2026-06-20",
      "selected_rank": 2,
      "player": "Arike Ogunbowale",
      "team": "DAL",
      "team_name": "Dallas Wings",
      "opponent": "CHI",
      "opponent_name": "Chicago Sky",
      "market": "THREES",
      "side": "OVER",
      "line": 1.5,
      "actual": null,
      "settlement": "PENDING",
      "model_probability": 0.64743,
      "final_score": 0.75476,
      "source_book": "fanduel",
      "source_url": "https://www.scoresandodds.com/wnba/props/3-pointers"
    },
    {
      "slate_date": "2026-06-20",
      "selected_rank": 3,
      "player": "Monique Akoa Makani",
      "team": "PHX",
      "team_name": "Phoenix Mercury",
      "opponent": "SEA",
      "opponent_name": "Seattle Storm",
      "market": "RA",
      "side": "UNDER",
      "line": 6.5,
      "actual": null,
      "settlement": "PENDING",
      "model_probability": 0.64495,
      "final_score": 0.6953,
      "source_book": "bet365",
      "source_url": "https://www.scoresandodds.com/wnba/props/rebounds-&-assists"
    },
    {
      "slate_date": "2026-06-20",
      "selected_rank": 4,
      "player": "Natasha Mack",
      "team": "PHX",
      "team_name": "Phoenix Mercury",
      "opponent": "SEA",
      "opponent_name": "Seattle Storm",
      "market": "PTS",
      "side": "UNDER",
      "line": 9.5,
      "actual": null,
      "settlement": "PENDING",
      "model_probability": 0.62054,
      "final_score": 0.67798,
      "source_book": "bet365",
      "source_url": "https://www.scoresandodds.com/wnba/props/points"
    }
  ]
}