{
  "generatedAt": "2026-05-29T18:19:15Z",
  "modelId": "wnba-player-prop-model-v1",
  "modelVersion": "2026-05-16-roster-slate-gate-v10",
  "cardGeneratedAt": "2026-05-28T21:26:48Z",
  "slateDate": "2026-05-28",
  "claimBoundary": "WNBA V1 uses historical boxscore logs plus supplied prop lines. It is a ranking and calibration model, not a guarantee. Live betting claims require current lines, player availability, and settled forward audit.",
  "summary": {
    "trackedPicks": 1,
    "settledPicks": 1,
    "pendingPicks": 0,
    "noActionPicks": 0,
    "wins": 0,
    "losses": 1,
    "pushes": 0,
    "accuracyPct": 0.0
  },
  "rows": [
    {
      "slate_date": "2026-05-28",
      "selected_rank": 1,
      "player": "Janelle Salaun",
      "team": "GS",
      "team_name": "Golden State Valkyries",
      "opponent": "IND",
      "opponent_name": "Indiana Fever",
      "market": "THREES",
      "side": "UNDER",
      "line": 2.5,
      "actual": 3.0,
      "settlement": "LOSS",
      "model_probability": 0.69045,
      "final_score": 0.87294,
      "source_book": "hardrock",
      "source_url": "https://www.scoresandodds.com/wnba/props/3-pointers"
    }
  ]
}